iota_dust_manager/__init__.py
iota_dust_manager-0.1.5.dist-info/LICENSE
iota_dust_manager-0.1.5.dist-info/METADATA
iota_dust_manager-0.1.5.dist-info/WHEEL
iota_dust_manager-0.1.5.dist-info/top_level.txt
iota_dust_manager-0.1.5.dist-info/RECORD
